wrtkit/__init__.py
wrtkit/base.py
wrtkit/cli.py
wrtkit/config.py
wrtkit/dhcp.py
wrtkit/firewall.py
wrtkit/fleet.py
wrtkit/fleet_executor.py
wrtkit/mesh.py
wrtkit/network.py
wrtkit/progress.py
wrtkit/schema.py
wrtkit/serial_connection.py
wrtkit/sqm.py
wrtkit/ssh.py
wrtkit/test_executor.py
wrtkit/testing.py
wrtkit/wireless.py
wrtkit-0.1.3.dist-info/licenses/LICENSE
wrtkit-0.1.3.dist-info/METADATA
wrtkit-0.1.3.dist-info/WHEEL
wrtkit-0.1.3.dist-info/entry_points.txt
wrtkit-0.1.3.dist-info/top_level.txt
wrtkit-0.1.3.dist-info/RECORD
