Metadata-Version: 2.4
Name: wrtkit
Version: 0.1.3
Summary: A Python library for managing OpenWRT configuration over SSH and serial
Author-email: Thibaut Lamadon <thibaut.lamadon@gmail.com>
License: MIT
Project-URL: Homepage, https://github.com/tlamadon/wrtkit
Project-URL: Documentation, https://github.com/tlamadon/wrtkit#readme
Project-URL: Repository, https://github.com/tlamadon/wrtkit
Project-URL: Issues, https://github.com/tlamadon/wrtkit/issues
Keywords: openwrt,uci,network,configuration,ssh,serial,console
Classifier: Development Status :: 3 - Alpha
Classifier: Intended Audience :: Developers
Classifier: Intended Audience :: System Administrators
Classifier: License :: OSI Approved :: MIT License
Classifier: Programming Language :: Python :: 3
Classifier: Programming Language :: Python :: 3.9
Classifier: Programming Language :: Python :: 3.10
Classifier: Programming Language :: Python :: 3.11
Classifier: Programming Language :: Python :: 3.12
Classifier: Topic :: System :: Networking
Classifier: Topic :: System :: Systems Administration
Requires-Python: >=3.9
License-File: LICENSE
Requires-Dist: paramiko>=3.0.0
Requires-Dist: pyserial>=3.5
Requires-Dist: pydantic>=2.0.0
Requires-Dist: pyyaml>=6.0.0
Requires-Dist: omegaconf>=2.3.0
Requires-Dist: click>=8.0.0
Requires-Dist: python-dotenv>=1.0.0
Provides-Extra: dev
Requires-Dist: pytest>=7.0.0; extra == "dev"
Requires-Dist: pytest-cov>=4.0.0; extra == "dev"
Requires-Dist: black>=23.0.0; extra == "dev"
Requires-Dist: ruff>=0.1.0; extra == "dev"
Requires-Dist: mypy>=1.0.0; extra == "dev"
Requires-Dist: types-paramiko>=3.0.0; extra == "dev"
Requires-Dist: types-pyserial>=3.0.0; extra == "dev"
Requires-Dist: types-pyyaml>=6.0.0; extra == "dev"
Requires-Dist: pre-commit>=3.0.0; extra == "dev"
Provides-Extra: docs
Requires-Dist: mkdocs>=1.5.0; extra == "docs"
Requires-Dist: mkdocs-material>=9.0.0; extra == "docs"
Requires-Dist: mkdocstrings[python]>=0.24.0; extra == "docs"
Dynamic: license-file
